janus/__init__.py
janus/constants/FileTag.py
janus/constants/workflow.py
janus/dto/__init__.py
janus/dto/collect_qc_request.py
janus/dto/collect_qc_response.py
janus/exceptions/__init__.py
janus/exceptions/exceptions.py
janus/io/read_json.py
janus/mappers/__init__.py
janus/mappers/tag_to_models.py
janus/mappers/tag_to_parse_function.py
janus/mappers/workflow_to_service.py
janus/models/multiqc/models.py
janus/models/workflow/balsamic.py
janus/server/__init__.py
janus/server/api.py
janus/server/app.py
janus/server/utils.py
janus/services/__init__.py
janus/services/collect_qc_service.py
janus/services/parser.py
janus/services/utils.py
janus/services/workflow_collect_qc_services.py
cg_janus-0.1.25.dist-info/METADATA
cg_janus-0.1.25.dist-info/WHEEL
cg_janus-0.1.25.dist-info/RECORD
