Metadata-Version: 2.3
Name: cg-janus
Version: 0.1.25
Summary: 
Author: Christian Oertlin
Author-email: c.oertlin@gmail.com
Requires-Python: >=3.11,<4.0
Classifier: Programming Language :: Python :: 3
Classifier: Programming Language :: Python :: 3.11
Classifier: Programming Language :: Python :: 3.12
Classifier: Programming Language :: Python :: 3.13
Requires-Dist: build (>=1.0.3,<2.0.0)
Requires-Dist: fastapi (>=0.109.2,<0.110.0)
Requires-Dist: gunicorn (>=21.2.0,<22.0.0)
Requires-Dist: mock (>=5.1.0,<6.0.0)
Requires-Dist: pydantic (>=2.6.0,<3.0.0)
Requires-Dist: pytest (>=8.0.0,<9.0.0)
Requires-Dist: sphinx (>=8.1.3,<9.0.0)
Requires-Dist: twine (>=4.0.2,<5.0.0)
Requires-Dist: uvicorn (>=0.27.1,<0.28.0)
Requires-Dist: wheel (>=0.42.0,<0.43.0)
Project-URL: Homepage, https://github.com/Clinical-Genomics/janus
Project-URL: Repository, https://github.com/Clinical-Genomics/janus
